rfkadapter/__init__.py
rfkadapter/rfkadapter.py
rfkadapter-0.3.7.dist-info/LICENSE
rfkadapter-0.3.7.dist-info/METADATA
rfkadapter-0.3.7.dist-info/WHEEL
rfkadapter-0.3.7.dist-info/top_level.txt
rfkadapter-0.3.7.dist-info/RECORD
