Metadata-Version: 2.1
Name: rfkadapter
Version: 0.3.7
Summary: RFKAdapter emulates a SQL-like CRUD API for DBF
Home-page: https://github.com/koljenovic/rfk
Author: Malik Koljenović
Author-email: malik@mekom.ba
Project-URL: Bug Tracker, https://github.com/koljenovic/rfk/issues
Classifier: Programming Language :: Python :: 3
Classifier: License :: OSI Approved :: MIT License
Classifier: Operating System :: OS Independent
Classifier: Development Status :: 4 - Beta
Classifier: Natural Language :: Bosnian
Classifier: Natural Language :: English
Classifier: Programming Language :: Other
Classifier: Topic :: Software Development :: Libraries :: Python Modules
Classifier: Topic :: Database :: Front-Ends
Requires-Python: >=3.7
License-File: LICENSE
